airbyte_cdk/__init__.py
airbyte_cdk/connector.py
airbyte_cdk/entrypoint.py
airbyte_cdk/exception_handler.py
airbyte_cdk/logger.py
airbyte_cdk/destinations/__init__.py
airbyte_cdk/destinations/destination.py
airbyte_cdk/models/__init__.py
airbyte_cdk/models/airbyte_protocol.py
airbyte_cdk/sources/__init__.py
airbyte_cdk/sources/abstract_files_source.py
airbyte_cdk/sources/abstract_source.py
airbyte_cdk/sources/config.py
airbyte_cdk/sources/source.py
airbyte_cdk/sources/declarative/__init__.py
airbyte_cdk/sources/declarative/create_partial.py
airbyte_cdk/sources/declarative/declarative_source.py
airbyte_cdk/sources/declarative/declarative_stream.py
airbyte_cdk/sources/declarative/types.py
airbyte_cdk/sources/declarative/yaml_declarative_source.py
airbyte_cdk/sources/declarative/auth/__init__.py
airbyte_cdk/sources/declarative/auth/oauth.py
airbyte_cdk/sources/declarative/checks/__init__.py
airbyte_cdk/sources/declarative/checks/check_stream.py
airbyte_cdk/sources/declarative/checks/connection_checker.py
airbyte_cdk/sources/declarative/datetime/__init__.py
airbyte_cdk/sources/declarative/datetime/min_max_datetime.py
airbyte_cdk/sources/declarative/decoders/__init__.py
airbyte_cdk/sources/declarative/decoders/decoder.py
airbyte_cdk/sources/declarative/decoders/json_decoder.py
airbyte_cdk/sources/declarative/extractors/__init__.py
airbyte_cdk/sources/declarative/extractors/http_selector.py
airbyte_cdk/sources/declarative/extractors/jello.py
airbyte_cdk/sources/declarative/extractors/record_filter.py
airbyte_cdk/sources/declarative/extractors/record_selector.py
airbyte_cdk/sources/declarative/interpolation/__init__.py
airbyte_cdk/sources/declarative/interpolation/interpolated_boolean.py
airbyte_cdk/sources/declarative/interpolation/interpolated_mapping.py
airbyte_cdk/sources/declarative/interpolation/interpolated_string.py
airbyte_cdk/sources/declarative/interpolation/interpolation.py
airbyte_cdk/sources/declarative/interpolation/jinja.py
airbyte_cdk_PHLAIR-0.2.3.dist-info/LICENSE.txt
airbyte_cdk_PHLAIR-0.2.3.dist-info/METADATA
airbyte_cdk_PHLAIR-0.2.3.dist-info/WHEEL
airbyte_cdk_PHLAIR-0.2.3.dist-info/top_level.txt
airbyte_cdk_PHLAIR-0.2.3.dist-info/RECORD
