Metadata-Version: 2.1
Name: airbyte-cdk-PHLAIR
Version: 0.2.3
Summary: A framework for writing Airbyte Connectors.
Home-page: https://github.com/airbytehq/airbyte
Author: Airbyte
Author-email: contact@airbyte.io
License: MIT
Project-URL: Documentation, https://docs.airbyte.io/
Project-URL: Source, https://github.com/airbytehq/airbyte
Project-URL: Tracker, https://github.com/airbytehq/airbyte/issues
Keywords: airbyte connector-development-kit cdk
Classifier: Development Status :: 3 - Alpha
Classifier: Intended Audience :: Developers
Classifier: Topic :: Scientific/Engineering
Classifier: Topic :: Software Development :: Libraries :: Python Modules
Classifier: License :: OSI Approved :: MIT License
Classifier: Programming Language :: Python :: 3.9
Requires-Python: >=3.9
License-File: LICENSE.txt
Requires-Dist: backoff
Requires-Dist: dpath (~=2.0.1)
Requires-Dist: jsonschema (~=3.2.0)
Requires-Dist: jsonref (~=0.2)
Requires-Dist: pendulum
Requires-Dist: pydantic (~=1.6)
Requires-Dist: PyYAML (~=5.4)
Requires-Dist: requests
Requires-Dist: vcrpy
Requires-Dist: Deprecated (~=1.2)
Requires-Dist: Jinja2 (~=3.1.2)
Requires-Dist: jello (~=1.5.2)
Provides-Extra: dev
Requires-Dist: backoff ; extra == 'dev'
Requires-Dist: dpath (~=2.0.1) ; extra == 'dev'
Requires-Dist: jsonschema (~=3.2.0) ; extra == 'dev'
Requires-Dist: jsonref (~=0.2) ; extra == 'dev'
Requires-Dist: pendulum ; extra == 'dev'
Requires-Dist: pydantic (~=1.6) ; extra == 'dev'
Requires-Dist: PyYAML (~=5.4) ; extra == 'dev'
Requires-Dist: requests ; extra == 'dev'
Requires-Dist: vcrpy ; extra == 'dev'
Requires-Dist: Deprecated (~=1.2) ; extra == 'dev'
Requires-Dist: Jinja2 (~=3.1.2) ; extra == 'dev'
Requires-Dist: jello (~=1.5.2) ; extra == 'dev'
Requires-Dist: pyarrow (~=8.0.0) ; extra == 'dev'
Requires-Dist: wcmatch (~=8.2) ; extra == 'dev'
Requires-Dist: dill (~=0.3.5) ; extra == 'dev'
Requires-Dist: fastavro (~=1.4.11) ; extra == 'dev'
Requires-Dist: python-snappy (~=0.6.1) ; extra == 'dev'
Requires-Dist: pandas (~=1.3.1) ; extra == 'dev'
Requires-Dist: avro (~=1.11.0) ; extra == 'dev'
Requires-Dist: Sphinx (~=4.2) ; extra == 'dev'
Requires-Dist: sphinx-rtd-theme (~=1.0) ; extra == 'dev'
Requires-Dist: MyPy (~=0.812) ; extra == 'dev'
Requires-Dist: pytest ; extra == 'dev'
Requires-Dist: pytest-cov ; extra == 'dev'
Requires-Dist: pytest-mock ; extra == 'dev'
Requires-Dist: pytest-order ; extra == 'dev'
Requires-Dist: requests-mock ; extra == 'dev'
Requires-Dist: pytest-httpserver ; extra == 'dev'
Provides-Extra: files-source
Requires-Dist: pyarrow (~=8.0.0) ; extra == 'files-source'
Requires-Dist: wcmatch (~=8.2) ; extra == 'files-source'
Requires-Dist: dill (~=0.3.5) ; extra == 'files-source'
Requires-Dist: fastavro (~=1.4.11) ; extra == 'files-source'
Requires-Dist: python-snappy (~=0.6.1) ; extra == 'files-source'
Requires-Dist: pandas (~=1.3.1) ; extra == 'files-source'
Requires-Dist: avro (~=1.11.0) ; extra == 'files-source'
Provides-Extra: sphinx-docs
Requires-Dist: Sphinx (~=4.2) ; extra == 'sphinx-docs'
Requires-Dist: sphinx-rtd-theme (~=1.0) ; extra == 'sphinx-docs'
